{"meta_robots": "", "meta_title": "Job Search Welcome | IBM Careers", "status": 200, "url": "https://krb-sjobs.brassring.com/TGnewUI/Search/Home/Home?partnerid=26059&siteid=5016", "encoding": "utf-8", "last_modified": null, "text_raw": "https://krb- sjobs.brassring.com/TGnewUI/Search/Home/Home?partnerid=26059&siteid=5016 Skip to the first action element of main content Loading We're sorry, this link is no longer valid.\nClose Your session has expired due to inactivity.\nBack Save this search {{refineResultsText}} {{jobsHeading}} {{jobsHeading}} {{jobsHeading}} {{filtersAppliedText}} {{facet.Description}} {{op.OptionName}}Remove selection {{facet.Description}} {{op.OptionName}} {{tgSettings.SortTextLabel}} Shortcuts After your selection, please press ESC key in order to apply or take other actions.\nLoading {{oQ.Value}} Featured Job Allows Referral {{dynamicStrings.LblJobShare.replace JobTitle ',oQ.Value }} {{dynamicStrings.LblJobURL.replace JobTitle ',oQ.Value }} {{dynamicStrings.LblCopyJobShare.replace JobTitle ',oQ.Value }} {{dynamicStrings.LblCloseJobShare.replace JobTitle ',oQ.Value }} {{tgSettings.ShowMoreText}} {{tgSettings.SearchResultsApplyToJobButtonText}} Save {{sendToFriendButtonText}} Refer Back You have already applied for this job.\nCheck application statusCheck your applications.\nApplication limit reached.\n{{LimitExceededMessage}} Close Featured Job Allows Referral Previous Job There are no previous jobs in this list.\nSwipe left and right to navigate between previous and next jobs.\nShare Job share URL Copy Job URL Close Job share dialog.\nFeatured Job Allows Referral Job Search Welcome IBM Careers View application statusView your applications {{tgSettings.JobDetailsApplyButtonText}} Save {{jobDetailsButtonText}} Refer The job posting you are looking for has expired or the position has already been filled.\nIf you are interested in one of our other opportunities, please visit our career site.\nCheck application statusCheck your applications.\nWe are experiencing an issue with our job search.\nPlease try again later.\nFeatured Job Allows Referral Next Job There are no next jobs in this list.\nBack We're sorry ...\nWe only allow one application for this job and you have already applied to: {{ErrorMessageJobTitle}} Application limit reached.\n{{LimitExceededMessage}} {{ErrorMessageJobTitle}} Scroll to top\n"}