{"meta_robots": "", "meta_title": "Language Of Emotional Intell - Segal - Google Books", "status": 200, "url": "https://books.google.com.pk/books?id=KSMa66pjercC&pg=PA214&lpg=PA214&dq=intell&source=bl&ots=OL5zuhcgBc&sig=ACfU3U082GWqM2CI6FkOV03ZTQqXhLxHZA&hl=en&sa=X&ved=2ahUKEwjrsvDMorTpAhV05eAKHUahAzU4ChDoATACegQICRAB", "encoding": "ascii", "last_modified": null, "text_raw": "Search Images Play YouTube News Gmail Drive Calendar More Sign in Books 1.\nMy library 2.\nPage 214| ---|---|--- ---|--- ---\n"}